CHANGES.rst
MANIFEST.in
README.rst
setup.py
django_logtail/__init__.py
django_logtail/admin.py
django_logtail/app_settings.py
django_logtail/models.py
django_logtail/tests.py
django_logtail/urls.py
django_logtail.egg-info/PKG-INFO
django_logtail.egg-info/SOURCES.txt
django_logtail.egg-info/dependency_links.txt
django_logtail.egg-info/not-zip-safe
django_logtail.egg-info/requires.txt
django_logtail.egg-info/top_level.txt
django_logtail/static/logtail/css/logtail.css
django_logtail/static/logtail/js/logtail.js
django_logtail/templates/logtail/logtail_list.html