Metadata-Version: 1.0
Name: django-logtail
Version: 0.1.1
Summary: A log viewing and tailing utility accessible via a Django admin panel
Home-page: https://github.com/alex2/django_logtail
Author: Alex Holmes
Author-email: alex.holmes@isotoma.com
License: The MIT License
Keywords: django admin logfile viewer tail log
Platform: UNKNOWN
